yaml_parser_annek/main.py
yaml_parser_annek-0.1.3.dist-info/METADATA
yaml_parser_annek-0.1.3.dist-info/WHEEL
yaml_parser_annek-0.1.3.dist-info/entry_points.txt
yaml_parser_annek-0.1.3.dist-info/RECORD
