Metadata-Version: 2.3
Name: yaml-parser-annek
Version: 0.1.3
Summary: Parse Yaml Files
License: MIT
Author: Mike Mackenna
Author-email: mmackenna@unitedfiregroup.com
Requires-Python: >=3.13
Classifier: License :: OSI Approved :: MIT License
Classifier: Programming Language :: Python :: 3
Classifier: Programming Language :: Python :: 3.13
Requires-Dist: dotenv (>=0.9.9,<0.10.0)
Requires-Dist: pydantic (>=2.11.7,<3.0.0)
Requires-Dist: pyyaml (>=6.0.2,<7.0.0)
Requires-Dist: typer (>=0.16.0,<0.17.0)
